PassivePySrc/PassivePy.py
PassivePySrc/__init__.py
PassivePySrc/rules_for_all_passives.py
PassivePySrc/rules_for_full_passives.py
PassivePySrc/rules_for_truncated_passives.py
PassivePy-0.2.21.dist-info/LICENSE
PassivePy-0.2.21.dist-info/METADATA
PassivePy-0.2.21.dist-info/WHEEL
PassivePy-0.2.21.dist-info/top_level.txt
PassivePy-0.2.21.dist-info/RECORD
