Metadata-Version: 2.1
Name: PassivePy
Version: 0.2.21
Summary: A package for processing large corpora and detecting passive voice.
Home-page: https://github.com/mitramir55/PassivePy
Author: Mitra Mirshafiee
Author-email: mitra.mirshafiee@gmail.com
Project-URL: Bug Tracker, https://github.com/pypa/sampleproject/issues
Keywords: passive voice,text analysis,spacy,dependency parsing,part of speech tagging
Classifier: Development Status :: 3 - Alpha
Classifier: Programming Language :: Python :: 3
Classifier: License :: OSI Approved :: MIT License
Classifier: Operating System :: OS Independent
Requires-Python: >=3.6
License-File: LICENSE
Requires-Dist: termcolor
Requires-Dist: tqdm
Requires-Dist: spacy (>=3.0.0)
